LICENSE.txt
MANIFEST.in
README.md
setup.py
configs/mangrove_forest.txt
configs/multiple_vegetation.txt
configs/salt_marsh.txt
wave_vegetation_1d/__init__.py
wave_vegetation_1d/cli.py
wave_vegetation_1d/py.typed
wave_vegetation_1d.egg-info/PKG-INFO
wave_vegetation_1d.egg-info/SOURCES.txt
wave_vegetation_1d.egg-info/dependency_links.txt
wave_vegetation_1d.egg-info/entry_points.txt
wave_vegetation_1d.egg-info/requires.txt
wave_vegetation_1d.egg-info/top_level.txt
wave_vegetation_1d/core/__init__.py
wave_vegetation_1d/core/config.py
wave_vegetation_1d/core/integration.py
wave_vegetation_1d/core/io.py
wave_vegetation_1d/core/solver.py
wave_vegetation_1d/core/spatial.py