Metadata-Version: 2.4
Name: wave-vegetation-1d
Version: 2.0.0
Summary: High-accuracy 1D wave propagation model through vegetated coastal areas
Home-page: https://github.com/sandyherho/wave-veg-1d
Author: Sandy Herho, Iwan Anwar
Author-email: sandy.herho@email.ucr.edu
Requires-Python: >=3.8
License-File: LICENSE.txt
Requires-Dist: numpy>=1.20.0
Requires-Dist: scipy>=1.7.0
Requires-Dist: xarray>=0.19.0
Requires-Dist: netCDF4>=1.5.7
Dynamic: author
Dynamic: author-email
Dynamic: description
Dynamic: description-content-type
Dynamic: home-page
Dynamic: license-file
Dynamic: requires-dist
Dynamic: requires-python
Dynamic: summary
